gopappy/__init__.py
gopappy/api.py
gopappy/auth.py
gopappy/cli.py
gopappy/colorize.py
gopappy-1.8.0.dist-info/LICENSE
gopappy-1.8.0.dist-info/METADATA
gopappy-1.8.0.dist-info/WHEEL
gopappy-1.8.0.dist-info/entry_points.txt
gopappy-1.8.0.dist-info/RECORD
