Metadata-Version: 2.1
Name: gopappy
Version: 1.8.0
Summary: GoDaddy v1 API implementation with secured auth token.
License: MIT
Author: Gamaliel Espinoza
Author-email: gamaliel.espinoza@gmail.com
Requires-Python: >=3.11,<3.13
Classifier: License :: OSI Approved :: MIT License
Classifier: Programming Language :: Python :: 3
Classifier: Programming Language :: Python :: 3.11
Classifier: Programming Language :: Python :: 3.12
Requires-Dist: colorama (>=0.4.6,<0.5.0)
Requires-Dist: keyring (>=24.3.1,<25.0.0)
Requires-Dist: keyrings-alt (>=5.0.2,<6.0.0)
Requires-Dist: pycryptodome (>=3.19.1,<4.0.0)
Requires-Dist: python-decouple (>=3.8,<4.0)
Requires-Dist: requests (>=2.31.0,<3.0.0)
Requires-Dist: typer (>=0.9.0,<0.10.0)
Requires-Dist: wheel (>=0.43.0,<0.44.0)
